spongecake/__init__.py
spongecake/_exceptions.py
spongecake/agent.py
spongecake/constants.py
spongecake/desktop.py
spongecake/trace.py
spongecake/telemetry/__init__.py
spongecake/telemetry/service.py
spongecake-0.1.15.dist-info/METADATA
spongecake-0.1.15.dist-info/WHEEL
spongecake-0.1.15.dist-info/top_level.txt
spongecake-0.1.15.dist-info/RECORD
