Metadata-Version: 2.4
Name: spongecake
Version: 0.1.15
Summary: Spongecake is the easiest way to launch OpenAI computer use agents.
Home-page: https://github.com/aditya-nadkarni/spongecake
Author: Terrell Marshall
Author-email: Terrell Marshall <terrell@passage-team.com>, Aditya Nadkarni <aditya@passage-team.com>
Keywords: sdk,browser,fastapi
Classifier: Programming Language :: Python :: 3
Classifier: License :: OSI Approved :: MIT License
Classifier: Operating System :: OS Independent
Requires-Python: >=3.9
Requires-Dist: requests>=2.0.0
Requires-Dist: httpx>=0.27.0
Requires-Dist: docker>=6.0.0
Requires-Dist: openai>=1.66.3
Requires-Dist: python-dotenv>=0.17.1
Requires-Dist: marionette-driver>=3.0.0
Requires-Dist: pyautogui>=0.9.54
Requires-Dist: posthog>=3.0.0
Dynamic: author
Dynamic: home-page
Dynamic: requires-python
